nfllivepy/__init__.py
nfllivepy/requester/__init__.py
nfllivepy/requester/errors.py
nfllivepy/requester/pbp_clean.py
nfllivepy/requester/pbp_requester.py
nfllivepy/requester/teams.py
nfllivepy/requester/util.py
nfllivepy-0.1.0.dist-info/LICENSE
nfllivepy-0.1.0.dist-info/METADATA
nfllivepy-0.1.0.dist-info/WHEEL
nfllivepy-0.1.0.dist-info/top_level.txt
nfllivepy-0.1.0.dist-info/RECORD
