Metadata-Version: 2.1
Name: nfllivepy
Version: 0.1.0
Summary: Package for obtaining live nfl play by play data
Author-email: Josh Kazan <jlkazan@gmail.com>
License: MIT License
Project-URL: Homepage, https://github.com/jlkazan/nfllivepy
Keywords: nfl,pbp
Classifier: License :: OSI Approved :: MIT License
Classifier: Programming Language :: Python
Classifier: Programming Language :: Python :: 3
Requires-Python: >=3.8
License-File: LICENSE
Requires-Dist: json-flatten
Requires-Dist: pandas
Requires-Dist: pendulum
Requires-Dist: requests
